yogger/__init__.py
yogger/base.py
yogger/compat.py
yogger/constants.py
yogger/pformat.py
yogger-0.0.7.dist-info/LICENSE
yogger-0.0.7.dist-info/METADATA
yogger-0.0.7.dist-info/WHEEL
yogger-0.0.7.dist-info/top_level.txt
yogger-0.0.7.dist-info/RECORD
