Metadata-Version: 2.1
Name: yogger
Version: 0.0.7
Summary: Minimal logging setup with utilities to represent interpreter stacks.
Author-email: The Phosmic Development Team <dev@phosmic.com>
License: GNU GENERAL PUBLIC LICENSE
Project-URL: homepage, https://pypi.org/project/yogger/
Project-URL: repository, https://github.com/Phosmic/yogger
Project-URL: issues, https://github.com/Phosmic/yogger/issues
Keywords: logging,inspect,trace,stack,locals,dump,dumps,yogger
Classifier: Development Status :: 3 - Alpha
Classifier: Intended Audience :: Developers
Classifier: License :: OSI Approved :: GNU General Public License v3 or later (GPLv3+)
Classifier: Natural Language :: English
Classifier: Operating System :: OS Independent
Classifier: Programming Language :: Python
Classifier: Programming Language :: Python :: 3
Classifier: Programming Language :: Python :: 3 :: Only
Classifier: Programming Language :: Python :: 3.10
Classifier: Programming Language :: Python :: 3.11
Classifier: Topic :: Utilities
Classifier: Topic :: System :: Logging
Classifier: Topic :: Software Development
Classifier: Topic :: Software Development :: Libraries
Classifier: Topic :: Software Development :: Libraries :: Python Modules
Requires-Python: <4,>=3.10
License-File: LICENSE
Provides-Extra: all
Requires-Dist: requests ; extra == 'all'
Provides-Extra: requests
Requires-Dist: requests ; extra == 'requests'
